{
  "id": "erdos-951",
  "source": "erdos",
  "sourceRef": {
    "edition": null,
    "url": "",
    "citation": "erdosproblems.com (T. Bloom)",
    "lean4Ref": "data/external-oss/formal-conjectures/FormalConjectures/ErdosProblems/951.lean"
  },
  "statement": {
    "en": "Erdős Problem 951",
    "ja": null,
    "latex": "A sequence `a : ℕ → ℝ` is said to have property `Erdos951Prop` if for any pair of distinct\nfinitely supported sequences `k l : ℕ →₀ ℕ` their corresponding Beurling integers are of distance\nat least one apart. -/\ndef Erdos951Prop (a : ℕ → ℝ) : Prop :=\n  ∀ (k ℓ : ℕ →₀ ℕ), k ≠ ℓ → |beurlingInteger a k - beurlingInteger a ℓ| ≥ 1\n\n/-- If `a` has property `Erdos951Prop` and `1 < a 0`, then `a` is a set ",
    "preview_source": "formal-conjectures"
  },
  "field": "number_theory",
  "subfield": null,
  "proposer": null,
  "year": null,
  "status": "unknown",
  "lastUpdate": "2026-04-23",
  "reiTyping": {
    "primaryType": "I_INFINITE_SEARCH",
    "secondaryType": null,
    "dfumt8": "NEITHER",
    "dfumt8Reason": "heuristic match on statement; I_INFINITE_SEARCH type",
    "rationale": "型=無限探索空間, D-FUMT₈=NEITHER; 形式化=easy (sorry=2)",
    "confidence": "NEITHER"
  },
  "cross_refs": {
    "wikipedia": null,
    "oeis": [],
    "mathlib": null,
    "external": [],
    "seedKernel": "T-2087"
  },
  "formalization": {
    "lean4": "scaffold",
    "coq": "none",
    "agda": "none",
    "isabelle": "none",
    "sorryCount": 2,
    "notes": "Namespaces: Erdos951"
  },
  "known_progress": [],
  "reiAssessment": {
    "mandalaPredicted": null,
    "approachSuggestion": null,
    "paperCandidate": false,
    "priority": "medium",
    "solveProbability": 0.6,
    "solveRationale": "Familiar=False, type=I_INFINITE_SEARCH, dfumt8=NEITHER, formalization=easy",
    "formalizationComplexity": "easy",
    "formalizationNotes": null,
    "reiFamiliarRef": null,
    "famousHardCap": null
  },
  "ingested": "2026-04-23",
  "ingestMethod": "phase-a-1-formal-conjectures-v1",
  "reviewer": null
}