{
  "id": "greens-60",
  "source": "greens",
  "sourceRef": {
    "edition": null,
    "url": "https://people.maths.ox.ac.uk/greenbj/papers/open-problems.pdf#section.8 Problem 60",
    "citation": "B. Green, Open Problems in Mathematics",
    "lean4Ref": "data/external-oss/formal-conjectures/FormalConjectures/GreensOpenProblems/60.lean"
  },
  "statement": {
    "en": "Ben Green's Open Problem 60",
    "ja": null,
    "latex": "Is there an absolute constant $c > 0$ such that, whenever $A ⊆ \\mathbb{N}$ is a set of squares\nwith $|A| ≥ 2$, the sumset $A + A$ satisfies $|A + A| ≥ |A|^{1 + c}$?",
    "preview_source": "formal-conjectures"
  },
  "field": "number_theory",
  "subfield": null,
  "proposer": null,
  "year": null,
  "status": "open",
  "lastUpdate": "2026-04-23",
  "reiTyping": {
    "primaryType": "I_INFINITE_SEARCH",
    "secondaryType": null,
    "dfumt8": "ZERO",
    "dfumt8Reason": "heuristic match on statement; I_INFINITE_SEARCH type",
    "rationale": "型=無限探索空間, D-FUMT₈=ZERO; 形式化=easy (sorry=1)",
    "confidence": "NEITHER"
  },
  "cross_refs": {
    "wikipedia": null,
    "oeis": [],
    "mathlib": null,
    "external": [],
    "seedKernel": "T-2128"
  },
  "formalization": {
    "lean4": "scaffold",
    "coq": "none",
    "agda": "none",
    "isabelle": "none",
    "sorryCount": 1,
    "notes": "Namespaces: Green60"
  },
  "known_progress": [],
  "reiAssessment": {
    "mandalaPredicted": null,
    "approachSuggestion": null,
    "paperCandidate": false,
    "priority": "medium",
    "solveProbability": 0.5,
    "solveRationale": "Familiar=False, type=I_INFINITE_SEARCH, dfumt8=ZERO, formalization=easy",
    "formalizationComplexity": "easy",
    "formalizationNotes": null,
    "reiFamiliarRef": null,
    "famousHardCap": null
  },
  "ingested": "2026-04-23",
  "ingestMethod": "phase-a-1-formal-conjectures-v1",
  "reviewer": null
}