{
  "id": "LATEST-GENERAL-2026-04-25-078",
  "tier": 7,
  "source": "business/general:W7120096317",
  "sourceRef": {
    "url": "https://doi.org/10.5281/zenodo.18197219",
    "citation": "O'ral HAYDAROV et al. 2026",
    "pdfUrl": "https://doi.org/10.5281/zenodo.18197219",
    "lean4Ref": null,
    "sourceCode": null
  },
  "statement": {
    "en": "O'ZBEKISTONDA RAQAMLI BANK XIZMATLARINING RIVOJLANISH TENDENSIYALARI",
    "ja": null,
    "latex": null,
    "preview_source": "tier7-ingest-v0.2",
    "summary": "Ushbu maqolada raqamli bank xizmatlarining mohiyati, ularning iqtisodiy ahamiyati hamda bank tizimida shakllanish va rivojlanish bosqichlari ilmiy-nazariy va amaliy jihatdan tahlil etilgan. Tadqiqot doirasida raqamli transformatsiya sharoitida bank xizmatlarini ko‘rsatishning an’anaviy shakllaridan raqamli platformalarga bosqichma-bosqich o‘tish jarayoni tahlil qilingan. Shuningdek, maqolada masofaviy bank xizmatlari, mobil va internet-banking tizimlarining rivojlanish tendensiyalari hamda ularning bank faoliyati samaradorligiga ta’siri ilmiy-nazariy va amaliy jihatdan yoritilgan."
  },
  "field": "business",
  "subfield": "general",
  "proposer": "O'ral HAYDAROV",
  "year": 2026,
  "status": "provisional",
  "lastUpdate": "2026-04-25",
  "reiTyping": {
    "primaryType": "FLOWING",
    "secondaryType": "FLOWING",
    "dfumt8": "FLOWING",
    "dfumt8Reason": "The paper presents a descriptive-analytical survey of digital banking service development trends in Uzbekistan as of 2026. It combines theoretical framework with empirical observation of an ongoing socioeconomic transformation. The claims are not yet peer-validated (preprint status indicated by future date anomaly), and digital banking evolution remains an active, non-convergent process. Classification as FLOWING reflects provisional knowledge in a dynamic domain.",
    "rationale": "classifier=haiku-4.5-v1.0",
    "confidence": 0.72
  },
  "cross_refs": {
    "arxiv": "W7120096317",
    "wikipedia": null,
    "oeis": [],
    "mathlib": null,
    "external": [],
    "seedKernel": null
  },
  "axiomMeta": {
    "lifecycleStage": "FLOWING",
    "provisionalityScore": 0.5,
    "expirationPolicy": "6-months",
    "sourceTier": "peer-reviewed-preprint",
    "sourceTrust": 0.75,
    "ontologicalCategory": "existing",
    "epistemologicalProperties": {
      "novelty": {
        "score": 0.7,
        "evidence": "preprint entry",
        "reviewedBy": "rule-based-v0.1"
      },
      "theoryType": {
        "score": 0.5,
        "evidence": "requires deeper analysis",
        "reducibleToExistingAxioms": null
      },
      "reproducibility": {
        "score": 0.5,
        "attempts": 0,
        "evidenceLevel": "preprint-only",
        "publicProtocol": null
      },
      "reconstructability": {
        "score": 0.3,
        "lean4Progress": "none",
        "axiomChainLength": null,
        "blockers": []
      }
    },
    "classificationDetail": {
      "formalizabilityClass": "CLASS-C",
      "sufficiencyStatus": "insufficient",
      "implementationPlan": "tbd",
      "blockers": []
    },
    "latestLinkage": {
      "seedKernelCandidate": [],
      "relatedTier1Problems": [],
      "relatedTier4Gaps": []
    },
    "peaceCheck": "passed"
  },
  "formalization": {
    "lean4": "none",
    "coq": "none",
    "agda": "none",
    "isabelle": "none",
    "sorryCount": null,
    "notes": null
  },
  "missingExecutableMeta": {
    "missingStatus": "partially-addressed",
    "possibilityStatus": "observation-only",
    "quadrant": "Q1",
    "missingKind": "theorem-or-empirical",
    "impossibilityEvidence": "none",
    "executabilityEffort": "unknown"
  },
  "ingested": "2026-04-25",
  "ingestMethod": "tier7-ingest-business-general-rule-based-v0.1",
  "intuitionArtifacts": {
    "ramanujanFormula": {
      "latex": "\\frac{\\text{Traditional}}{\\text{Digital}} \\to \\int_0^t e^{\\lambda s} \\, ds = \\frac{e^{\\lambda t}-1}{\\lambda}",
      "interpretation": "デジタル化は銀行の伝統的形態を指数関数的に融解し、時間とともに新しい平衡へ収束する。",
      "claimedRigor": "intuition-only"
    },
    "visualGlyph": {
      "type": "svg",
      "svg": "<svg viewBox='0 0 100 100' xmlns='http://www.w3.org/2000/svg'><circle cx='25' cy='50' r='12' stroke='#7c3aed' stroke-width='2' fill='none'/><circle cx='75' cy='50' r='12' stroke='#00d4ff' stroke-width='2' fill='none'/><path d='M 37 48 Q 50 35 63 52' stroke='#00ff88' stroke-width='2.5' fill='none' stroke-linecap='round'/><polyline points='50,30 50,15 40,20' stroke='#ec4899' stroke-width='1.5' fill='none'/><text x='50' y='75' font-size='10' text-anchor='middle' fill='#f59e0b' font-weight='bold'>flux</text></svg>",
      "interpretation": "伝統的な銀行（左）がデジタル流（中央）を通じて新しい生態系（右）へ光速で変形している。",
      "claimedRigor": "intuition-only"
    },
    "generatedBy": "haiku-4.5",
    "generatedDate": "2026-04-25"
  }
}
