{
  "id": "kourovka-19-67",
  "source": "kourovka",
  "sourceRef": {
    "edition": 19,
    "url": "https://arxiv.org/abs/1401.0300",
    "citation": "Kourovka Notebook, Problem 19.67 (Khukhro & Mazurov eds., ed.19)",
    "lean4Ref": null
  },
  "statement": {
    "en": "Kourovka Problem 19.67",
    "ja": null,
    "latex": "Let$G { Sym}( )$, where$$is finite. The$2$-closure$G^{(2)}$of the group$G$is defined to be the largest subgroup of${ Sym}( )$containing‾$G$which has the same orbits as‾$G$in the induced action on‾$$. Is it true that if$G$is solvable, then every composition factor of$G^{(2)}$is either a cyclic or an alternating group? { I.¥¥,Ponomarenko} No, it is not true (S.¥¥,V.¥¥,Skresanov, Algebra Logic, { 58}, n...",
    "preview_source": "kourovka-ed21-tex-parser",
    "full_text": null
  },
  "field": "group_theory",
  "subfield": null,
  "proposer": null,
  "year": null,
  "status": "open",
  "lastUpdate": "2026-04-23",
  "reiTyping": {
    "primaryType": "I_INFINITE_SEARCH",
    "secondaryType": null,
    "dfumt8": "NEITHER",
    "dfumt8Reason": "keyword heuristic + group-theory prior",
    "rationale": "Kourovka group theory problem; type=I_INFINITE_SEARCH",
    "confidence": "FLOWING"
  },
  "cross_refs": {
    "wikipedia": null,
    "oeis": [],
    "mathlib": null,
    "external": [],
    "seedKernel": null
  },
  "formalization": {
    "lean4": "none",
    "coq": "none",
    "agda": "none",
    "isabelle": "none",
    "sorryCount": null,
    "notes": null
  },
  "known_progress": [],
  "reiAssessment": {
    "mandalaPredicted": null,
    "approachSuggestion": null,
    "paperCandidate": false,
    "priority": "low",
    "solveProbability": 0.4,
    "solveRationale": "Group theory I_INFINITE_SEARCH; Rei not specialized in group theory (yet)",
    "formalizationComplexity": "hard",
    "formalizationNotes": "Kourovka problems are typically research-level group theory",
    "famousHardCap": null,
    "reiFamiliarRef": null
  },
  "ingested": "2026-04-23",
  "ingestMethod": "phase-b-kourovka-tex-v1",
  "reviewer": null
}