{
  "id": "kourovka-5-49",
  "source": "kourovka",
  "sourceRef": {
    "edition": 5,
    "url": "https://arxiv.org/abs/1401.0300",
    "citation": "Kourovka Notebook, Problem 5.49 (Khukhro & Mazurov eds., ed.5)",
    "lean4Ref": null
  },
  "statement": {
    "en": "Kourovka Problem 5.49",
    "ja": null,
    "latex": "Let$A_{m,n}$be the group of all automorphisms of the free soluble group of derived length$n$and rank$m$. Is it true that$A_{m,n}$is finitely generated for any$m$and$n$? every automorphism in$A_{m,n}$is induced by some automorphism in$A_{m,n+1}$? { V.\\,N.\\,Remeslennikov} a) No:$A_{3,2}$is not finitely generated, although$A_{m,2}$is whenever$m 3$(S.\\,Bachmuth, H.\\,Y.\\,Mochizuki, Trans. Amer. Math. S...",
    "preview_source": "kourovka-ed21-tex-parser",
    "full_text": null
  },
  "field": "group_theory",
  "subfield": null,
  "proposer": null,
  "year": null,
  "status": "open",
  "lastUpdate": "2026-04-23",
  "reiTyping": {
    "primaryType": "I_INFINITE_SEARCH",
    "secondaryType": null,
    "dfumt8": "NEITHER",
    "dfumt8Reason": "keyword heuristic + group-theory prior",
    "rationale": "Kourovka group theory problem; type=I_INFINITE_SEARCH",
    "confidence": "FLOWING"
  },
  "cross_refs": {
    "wikipedia": null,
    "oeis": [],
    "mathlib": null,
    "external": [],
    "seedKernel": null
  },
  "formalization": {
    "lean4": "none",
    "coq": "none",
    "agda": "none",
    "isabelle": "none",
    "sorryCount": null,
    "notes": null
  },
  "known_progress": [],
  "reiAssessment": {
    "mandalaPredicted": null,
    "approachSuggestion": null,
    "paperCandidate": false,
    "priority": "low",
    "solveProbability": 0.4,
    "solveRationale": "Group theory I_INFINITE_SEARCH; Rei not specialized in group theory (yet)",
    "formalizationComplexity": "hard",
    "formalizationNotes": "Kourovka problems are typically research-level group theory",
    "famousHardCap": null,
    "reiFamiliarRef": null
  },
  "ingested": "2026-04-23",
  "ingestMethod": "phase-b-kourovka-tex-v1",
  "reviewer": null
}