{
  "id": "LATEST-PHYSICS-2026-04-25-027",
  "tier": 7,
  "source": "science/physics:W7130823864",
  "sourceRef": {
    "url": "https://doi.org/10.5281/zenodo.18718273",
    "citation": "Nadav Bashan et al. 2026",
    "pdfUrl": "https://doi.org/10.5281/zenodo.18718273",
    "lean4Ref": null,
    "sourceCode": null
  },
  "statement": {
    "en": "The Holographic Boundary Principle: A Geometric Normalization from Stellar Photospheres to the Cosmic Horizon",
    "ja": null,
    "latex": null,
    "preview_source": "tier7-ingest-v0.2",
    "summary": "In this work, we present a geometric boundary framework that explicitly derives the gravitational relation (G) from the cosmological constant (Λ) through a scale-independent surface normalization. Starting from radiative decoupling surfaces, we identify a dimensionless boundary relation converging to the exact mass-independent identity π³/15. Extending this boundary condition to the cosmic horizon yields the master constraint ΛR_H² = π³/15. By incorporating holographic tiling of the horizon area, we extract an explicit algebraic expression for G, governed entirely by the discrete information bound (N) of the macroscopic surface. Within this formulation, the canonical ~ 10^120 vacuum-energy discrepancy is mathematically resolved not as an energy divergence, but as the exact dimensional scal"
  },
  "field": "science",
  "subfield": "physics",
  "proposer": "Nadav Bashan",
  "year": 2026,
  "status": "provisional",
  "lastUpdate": "2026-04-25",
  "reiTyping": {
    "primaryType": "FLOWING",
    "secondaryType": "FLOWING",
    "dfumt8": "FLOWING",
    "dfumt8Reason": "The paper proposes a novel derivation of gravitational constant G from cosmological parameters via holographic principles. It is not yet peer-reviewed (arxiv preprint status, 2026 future date suggests speculative metadata), contains specific mathematical claims (π³/15 identity, ΛR_H² relation) that require independent validation. The work presents internal logical structure but lacks external corroboration. Classification as FLOWING reflects provisional status pending community review and empirical/theoretical validation.",
    "rationale": "classifier=haiku-4.5-v1.0",
    "confidence": 0.35
  },
  "cross_refs": {
    "arxiv": "W7130823864",
    "wikipedia": null,
    "oeis": [],
    "mathlib": null,
    "external": [],
    "seedKernel": null
  },
  "axiomMeta": {
    "lifecycleStage": "FLOWING",
    "provisionalityScore": 0.5,
    "expirationPolicy": "6-months",
    "sourceTier": "peer-reviewed-preprint",
    "sourceTrust": 0.75,
    "ontologicalCategory": "can-be-made",
    "epistemologicalProperties": {
      "novelty": {
        "score": 0.7,
        "evidence": "preprint entry",
        "reviewedBy": "rule-based-v0.1"
      },
      "theoryType": {
        "score": 0.5,
        "evidence": "requires deeper analysis",
        "reducibleToExistingAxioms": null
      },
      "reproducibility": {
        "score": 0.5,
        "attempts": 0,
        "evidenceLevel": "preprint-only",
        "publicProtocol": null
      },
      "reconstructability": {
        "score": 0.3,
        "lean4Progress": "none",
        "axiomChainLength": null,
        "blockers": []
      }
    },
    "classificationDetail": {
      "formalizabilityClass": "CLASS-A",
      "sufficiencyStatus": "insufficient",
      "implementationPlan": "tbd",
      "blockers": []
    },
    "latestLinkage": {
      "seedKernelCandidate": [],
      "relatedTier1Problems": [],
      "relatedTier4Gaps": []
    },
    "peaceCheck": "passed"
  },
  "formalization": {
    "lean4": "none",
    "coq": "none",
    "agda": "none",
    "isabelle": "none",
    "sorryCount": null,
    "notes": null
  },
  "missingExecutableMeta": {
    "missingStatus": "partially-addressed",
    "possibilityStatus": "observation-only",
    "quadrant": "Q1",
    "missingKind": "theorem-or-empirical",
    "impossibilityEvidence": "none",
    "executabilityEffort": "unknown"
  },
  "ingested": "2026-04-25",
  "ingestMethod": "tier7-ingest-science-physics-rule-based-v0.1",
  "intuitionArtifacts": {
    "ramanujanFormula": {
      "latex": "G = \\frac{\\pi^3}{15} \\cdot \\frac{1}{\\Lambda R_H^2 N}",
      "interpretation": "重力定数は宇宙の地平線の離散情報から生まれる。",
      "claimedRigor": "intuition-only"
    },
    "visualGlyph": {
      "type": "svg",
      "svg": "<svg viewBox='0 0 100 100' xmlns='http://www.w3.org/2000/svg'><circle cx='50' cy='50' r='45' stroke='#00d4ff' stroke-width='2' fill='none'/><circle cx='50' cy='50' r='30' stroke='#7c3aed' stroke-width='1.5' fill='none'/><circle cx='50' cy='50' r='15' stroke='#ec4899' stroke-width='1' fill='none'/><polyline points='50,5 50,95' stroke='#ffd700' stroke-width='1' opacity='0.6'/><polyline points='5,50 95,50' stroke='#ffd700' stroke-width='1' opacity='0.6'/><g stroke='#00ff88' stroke-width='1' fill='none'><path d='M 50 35 Q 60 40 65 50 Q 60 60 50 65'/><path d='M 50 35 Q 40 40 35 50 Q 40 60 50 65'/></g><text x='50' y='85' text-anchor='middle' font-size='8' fill='#f59e0b'>π³/15</text></svg>",
      "interpretation": "地平線の離散タイルが重力を編む—観測者の視界の端が法則を決める。",
      "claimedRigor": "intuition-only"
    },
    "generatedBy": "haiku-4.5",
    "generatedDate": "2026-04-25"
  }
}
