{
  "id": "LATEST-BIOLOGY-2026-04-25-042",
  "tier": 7,
  "source": "science/biology:W7128635634",
  "sourceRef": {
    "url": "https://doi.org/10.17638/03194776",
    "citation": "Kim Van De Wiel et al. 2027",
    "pdfUrl": "https://doi.org/10.17638/03194776",
    "lean4Ref": null,
    "sourceCode": null
  },
  "statement": {
    "en": "Disease ecology at a wildlife-livestock interface: Gastrointestinal parasite sharing in wild and domestic African ungulates",
    "ja": null,
    "latex": null,
    "preview_source": "tier7-ingest-v0.2",
    "summary": ""
  },
  "field": "science",
  "subfield": "biology",
  "proposer": "Kim Van De Wiel",
  "year": 2027,
  "status": "provisional",
  "lastUpdate": "2026-04-25",
  "reiTyping": {
    "primaryType": "FLOWING",
    "secondaryType": "FLOWING",
    "dfumt8": "FLOWING",
    "dfumt8Reason": "The axiom concerns empirical disease ecology research at wildlife-livestock interfaces. This is an active field with ongoing data collection, validation, and interpretation. The 2026 date indicates this is recent/provisional work not yet through full peer-review cycles. Gastrointestinal parasite sharing dynamics are context-dependent and subject to environmental, seasonal, and population variables, making absolute truth-claims premature.",
    "rationale": "classifier=haiku-4.5-v1.0",
    "confidence": 0.62
  },
  "cross_refs": {
    "arxiv": "W7128635634",
    "wikipedia": null,
    "oeis": [],
    "mathlib": null,
    "external": [],
    "seedKernel": null
  },
  "axiomMeta": {
    "lifecycleStage": "FLOWING",
    "provisionalityScore": 0.5,
    "expirationPolicy": "6-months",
    "sourceTier": "peer-reviewed-preprint",
    "sourceTrust": 0.75,
    "ontologicalCategory": "existing",
    "epistemologicalProperties": {
      "novelty": {
        "score": 0.7,
        "evidence": "preprint entry",
        "reviewedBy": "rule-based-v0.1"
      },
      "theoryType": {
        "score": 0.5,
        "evidence": "requires deeper analysis",
        "reducibleToExistingAxioms": null
      },
      "reproducibility": {
        "score": 0.5,
        "attempts": 0,
        "evidenceLevel": "preprint-only",
        "publicProtocol": null
      },
      "reconstructability": {
        "score": 0.3,
        "lean4Progress": "none",
        "axiomChainLength": null,
        "blockers": []
      }
    },
    "classificationDetail": {
      "formalizabilityClass": "CLASS-B",
      "sufficiencyStatus": "insufficient",
      "implementationPlan": "tbd",
      "blockers": []
    },
    "latestLinkage": {
      "seedKernelCandidate": [],
      "relatedTier1Problems": [],
      "relatedTier4Gaps": []
    },
    "peaceCheck": "passed"
  },
  "formalization": {
    "lean4": "none",
    "coq": "none",
    "agda": "none",
    "isabelle": "none",
    "sorryCount": null,
    "notes": null
  },
  "missingExecutableMeta": {
    "missingStatus": "partially-addressed",
    "possibilityStatus": "observation-only",
    "quadrant": "Q1",
    "missingKind": "theorem-or-empirical",
    "impossibilityEvidence": "none",
    "executabilityEffort": "unknown"
  },
  "ingested": "2026-04-25",
  "ingestMethod": "tier7-ingest-science-biology-rule-based-v0.1",
  "intuitionArtifacts": {
    "ramanujanFormula": {
      "latex": "\\frac{\\partial P}{\\partial t} = \\alpha W \\cdot L + \\beta(W \\cap L) - \\gamma P",
      "interpretation": "野生動物と家畜の接触が寄生虫の流行を増幅させる、見えない橋のようだ。",
      "claimedRigor": "intuition-only"
    },
    "visualGlyph": {
      "type": "svg",
      "svg": "<svg viewBox='0 0 100 100' xmlns='http://www.w3.org/2000/svg'><circle cx='30' cy='50' r='20' stroke='#00d4ff' stroke-width='2' fill='none'/><circle cx='70' cy='50' r='20' stroke='#ec4899' stroke-width='2' fill='none'/><line x1='50' y1='50' x2='50' y2='30' stroke='#00ff88' stroke-width='2'/><line x1='50' y1='50' x2='50' y2='70' stroke='#00ff88' stroke-width='2'/><circle cx='50' cy='50' r='4' fill='#ffd700'/><path d='M 35 35 Q 50 40 65 35' stroke='#7c3aed' stroke-width='1.5' fill='none' opacity='0.6'/><path d='M 35 65 Q 50 60 65 65' stroke='#7c3aed' stroke-width='1.5' fill='none' opacity='0.6'/></svg>",
      "interpretation": "二つの個体群が接する場所で、寄生虫は静寂のうちに交換される。",
      "claimedRigor": "intuition-only"
    },
    "generatedBy": "haiku-4.5",
    "generatedDate": "2026-04-25"
  }
}
